unitypredict/UnityPredictClient.py
unitypredict/__init__.py
unitypredict-1.1.80.dist-info/METADATA
unitypredict-1.1.80.dist-info/WHEEL
unitypredict-1.1.80.dist-info/top_level.txt
unitypredict-1.1.80.dist-info/RECORD
