Metadata-Version: 2.4
Name: unitypredict
Version: 1.1.80
Summary:  
Home-page: https://unitypredict.com
Author: UnityPredict
License:  
Requires-Dist: attr
Requires-Dist: cattrs
Requires-Dist: requests
Dynamic: author
Dynamic: description
Dynamic: description-content-type
Dynamic: home-page
Dynamic: license
Dynamic: requires-dist
Dynamic: summary
